{
  "11": {
    "tracker": [
      [
        "CLIFF",
        "Sheffield Yd ",
        11
      ],
      [
        "BANK",
        "",
        3
      ],
      [
        "NASSAU",
        "Wilson City / N31 or N32 (S)",
        23
      ],
      [
        "",
        "Kurlish Jct",
        19
      ],
      [
        "SHORE",
        "",
        6
      ],
      [
        "DELL",
        "Laporte",
        21
      ],
      [
        "",
        "Carlton",
        15
      ],
      [
        "KRULISH",
        "Latham",
        10
      ],
      [
        "YARD",
        "Koehlstadt / Y51 (X)",
        1
      ]
    ],
    "block": null,
    "desc": "Express Passenger",
    "loco": null,
    "normalloco": null,
    "origin": {
      "loc": "CF",
      "track": null
    },
    "terminus": {
      "loc": "YD",
      "track": "Y51"
    },
    "sequence": [
      {
        "block": "C23",
        "os": "COSCLEW",
        "route": "CRtC23C22",
        "signal": "C10L",
        "time": 5000,
        "trigger": "Front"
      },
      {
        "block": "C13",
        "os": "COSCLW",
        "route": "CRtC13C23",
        "signal": "C14LB",
        "time": 5000,
        "trigger": "Front"
      },
      {
        "block": "B11",
        "os": "BOSE",
        "route": "BRtB11C13",
        "signal": "C18L",
        "time": 5000,
        "trigger": "Front"
      },
      {
        "block": "B10",
        "os": "BOSWW",
        "route": "BRtB10B11",
        "signal": "C22L",
        "time": 5000,
        "trigger": "Front"
      },
      {
        "block": "N31",
        "os": "NEOSW",
        "route": "NRtB10N31",
        "signal": "N26L",
        "time": 5000,
        "trigger": "Front"
      },
      {
        "block": "N11",
        "os": "NWOSW",
        "route": "NRtN11N31",
        "signal": "N18LB",
        "time": 5000,
        "trigger": "Front"
      },
      {
        "block": "N10",
        "os": "KOSW",
        "route": "KRtN10N11",
        "signal": "K8LB",
        "time": 5000,
        "trigger": "Front"
      },
      {
        "block": "S11",
        "os": "KOSN10S11",
        "route": "KRtN10S11",
        "signal": "N10W",
        "time": 5000,
        "trigger": "Front"
      },
      {
        "block": "S10",
        "os": "SOSW",
        "route": "SRtS10S11",
        "signal": "S12LA",
        "time": 5000,
        "trigger": "Front"
      },
      {
        "block": "D11",
        "os": "DOSFOW",
        "route": "DRtD11S10",
        "signal": "D12L",
        "time": 5000,
        "trigger": "Front"
      },
      {
        "block": "D10",
        "os": "DOSVJW",
        "route": "DRtD10D11",
        "signal": "D6L",
        "time": 5000,
        "trigger": "Front"
      },
      {
        "block": "L11",
        "os": "LOSCAW",
        "route": "LRtL11D10",
        "signal": "L18L",
        "time": 5000,
        "trigger": "Front"
      },
      {
        "block": "L10",
        "os": "LOSLAW",
        "route": "LRtL10L11",
        "signal": "L8L",
        "time": 5000,
        "trigger": "Front"
      },
      {
        "block": "Y11",
        "os": "YOSCJW",
        "route": "YRtY11L10",
        "signal": "Y2L",
        "time": 5000,
        "trigger": "Front"
      },
      {
        "block": "Y30",
        "os": "YOSEJW",
        "route": "YRtY30Y11",
        "signal": "Y8L",
        "time": 5000,
        "trigger": "Front"
      },
      {
        "block": "Y51",
        "os": "YOSKL4",
        "route": "YRtY30Y51",
        "signal": "Y34R",
        "time": 5000,
        "trigger": "Front"
      }
    ],
    "startblock": "C22",
    "startsubblock": null,
    "time": 5000,
    "eastbound": false
  },
  "12": {
    "tracker": [
      [
        "YARD",
        "Koehlstadt / Y51",
        1
      ],
      [
        "",
        "Cornell",
        7
      ],
      [
        "LATHAM",
        "Latham Jct",
        10
      ],
      [
        "DELL",
        "Laporte",
        21
      ],
      [
        "SHORE",
        "",
        5
      ],
      [
        "",
        "Krulish Jct",
        19
      ],
      [
        "NASSAU",
        "Wilson City / N41 or N42 (S)",
        23
      ],
      [
        "BANK",
        "",
        3
      ],
      [
        "CLIFF",
        "Sheffield Yd (X)",
        11
      ]
    ],
    "block": null,
    "desc": "Express Passenger",
    "loco": null,
    "normalloco": null,
    "origin": {
      "loc": "YD",
      "track": "Y51"
    },
    "terminus": {
      "loc": "CF",
      "track": null
    },
    "sequence": [
      {
        "block": "Y20",
        "os": "YOSKL1",
        "route": "YRtY20Y51",
        "signal": "Y26RB",
        "time": 5000,
        "trigger": "Front"
      },
      {
        "block": "Y21",
        "os": "YOSEJE",
        "route": "YRtY20Y21",
        "signal": "Y10R",
        "time": 5000,
        "trigger": "Front"
      },
      {
        "block": "L20",
        "os": "YOSCJE",
        "route": "YRtY21L20",
        "signal": "Y4R",
        "time": 5000,
        "trigger": "Front"
      },
      {
        "block": "L21",
        "os": "LOSLAM",
        "route": "LRtL20L21",
        "signal": "L6RA",
        "time": 5000,
        "trigger": "Front"
      },
      {
        "block": "D20",
        "os": "LOSCAM",
        "route": "LRtL21D20",
        "signal": "L16R",
        "time": 5000,
        "trigger": "Front"
      },
      {
        "block": "D21",
        "os": "DOSVJE",
        "route": "DRtD20D21",
        "signal": "D4RA",
        "time": 5000,
        "trigger": "Front"
      },
      {
        "block": "S20",
        "os": "DOSFOE",
        "route": "DRtD21S20",
        "signal": "D10R",
        "time": 5000,
        "trigger": "Front"
      },
      {
        "block": "S21",
        "os": "SOSE",
        "route": "SRtS20S21",
        "signal": "S4R",
        "time": 5000,
        "trigger": "Front"
      },
      {
        "block": "N20",
        "os": "KOSN20S21",
        "route": "KRtN20S21",
        "signal": "S21E",
        "time": 5000,
        "trigger": "Front"
      },
      {
        "block": "N21",
        "os": "KOSE",
        "route": "KRtN20N21",
        "signal": "K2R",
        "time": 5000,
        "trigger": "Front"
      },
      {
        "block": "N41",
        "os": "NWOSE",
        "route": "NRtN21N41",
        "signal": "N14R",
        "time": 5000,
        "trigger": "Front"
      },
      {
        "block": "B20",
        "os": "NEOSE",
        "route": "NRtB20N41",
        "signal": "N24RB",
        "time": 5000,
        "trigger": "Front"
      },
      {
        "block": "B21",
        "os": "BOSWE",
        "route": "BRtB20B21",
        "signal": "C24R",
        "time": 5000,
        "trigger": "Front"
      },
      {
        "block": "C13",
        "os": "BOSE",
        "route": "BRtB21C13",
        "signal": "C18RA",
        "time": 5000,
        "trigger": "Front"
      },
      {
        "block": "C12",
        "os": "COSCLW",
        "route": "CRtC13C12",
        "signal": "C14R",
        "time": 5000,
        "trigger": "Front"
      },
      {
        "block": "C11",
        "os": "COSCLEE",
        "route": "CRtC12C11",
        "signal": "C12R",
        "time": 5000,
        "trigger": "Front"
      },
      {
        "block": "C30",
        "os": "COSGMW",
        "route": "CRtC11C30",
        "signal": "C4R",
        "time": 5000,
        "trigger": "Front"
      },
      {
        "block": "C20",
        "os": "COSGME",
        "route": "CRtC30C20",
        "signal": "C2RA",
        "time": 5000,
        "trigger": "Front"
      }
    ],
    "startblock": "Y51",
    "startsubblock": null,
    "time": 5000,
    "eastbound": true
  },
  "17": {
    "tracker": [
      [
        "CLIFF",
        "Sheffield Yd",
        11
      ],
      [
        "",
        "Cliveden",
        10
      ],
      [
        "BANK",
        "",
        3
      ],
      [
        "NASSAU",
        "Wilson City / N31 or N32 (S)",
        23
      ],
      [
        "KRULISH",
        "Krulish Jct",
        19
      ],
      [
        "",
        "Radstock",
        14
      ],
      [
        "PORT",
        "Parsons Jct",
        9
      ],
      [
        "",
        "Cornell Jct",
        7
      ],
      [
        "YARD",
        "koehlstadt / Y50 (X)",
        11
      ]
    ],
    "block": null,
    "desc": "Express Passenger",
    "loco": null,
    "normalloco": null,
    "origin": {
      "loc": "CF",
      "track": null
    },
    "terminus": {
      "loc": "YD",
      "track": "Y50"
    },
    "sequence": [
      {
        "block": "C23",
        "os": "COSCLEW",
        "route": "CRtC23C22",
        "signal": "C10L",
        "time": 5000,
        "trigger": "Front"
      },
      {
        "block": "C13",
        "os": "COSCLW",
        "route": "CRtC13C23",
        "signal": "C14LB",
        "time": 5000,
        "trigger": "Front"
      },
      {
        "block": "B11",
        "os": "BOSE",
        "route": "BRtB11C13",
        "signal": "C18L",
        "time": 5000,
        "trigger": "Front"
      },
      {
        "block": "B10",
        "os": "BOSWW",
        "route": "BRtB10B11",
        "signal": "C22L",
        "time": 5000,
        "trigger": "Front"
      },
      {
        "block": "N31",
        "os": "NEOSW",
        "route": "NRtB10N31",
        "signal": "N26L",
        "time": 5000,
        "trigger": "Front"
      },
      {
        "block": "N11",
        "os": "NWOSW",
        "route": "NRtN11N31",
        "signal": "N18LB",
        "time": 5000,
        "trigger": "Front"
      },
      {
        "block": "N10",
        "os": "KOSW",
        "route": "KRtN10N11",
        "signal": "K8LB",
        "time": 5000,
        "trigger": "Front"
      },
      {
        "block": "S11",
        "os": "KOSN10S11",
        "route": "KRtN10S11",
        "signal": "N10W",
        "time": 5000,
        "trigger": "Front"
      },
      {
        "block": "S10",
        "os": "SOSW",
        "route": "SRtS10S11",
        "signal": "S12LA",
        "time": 5000,
        "trigger": "Front"
      },
      {
        "block": "D11",
        "os": "DOSFOW",
        "route": "DRtD11S10",
        "signal": "D12L",
        "time": 5000,
        "trigger": "Front"
      },
      {
        "block": "D10",
        "os": "DOSVJW",
        "route": "DRtD10D11",
        "signal": "D6L",
        "time": 5000,
        "trigger": "Front"
      },
      {
        "block": "L11",
        "os": "LOSCAW",
        "route": "LRtL11D10",
        "signal": "L18L",
        "time": 5000,
        "trigger": "Front"
      },
      {
        "block": "L10",
        "os": "LOSLAW",
        "route": "LRtL10L11",
        "signal": "L8L",
        "time": 5000,
        "trigger": "Front"
      },
      {
        "block": "Y11",
        "os": "YOSCJW",
        "route": "YRtY11L10",
        "signal": "Y2L",
        "time": 5000,
        "trigger": "Front"
      },
      {
        "block": "Y30",
        "os": "YOSEJW",
        "route": "YRtY30Y11",
        "signal": "Y8L",
        "time": 5000,
        "trigger": "Front"
      },
      {
        "block": "Y50",
        "os": "YOSKL4",
        "route": "YRtY30Y50",
        "signal": "Y34R",
        "time": 5000,
        "trigger": "Front"
      }
    ],
    "startblock": "C22",
    "startsubblock": null,
    "time": 5000,
    "eastbound": false
  },
  "18": {
    "tracker": [
      [
        "YARD",
        "Koehlstadt / Y50",
        1
      ],
      [
        "",
        "Cornell Jct",
        7
      ],
      [
        "PORT",
        "",
        9
      ],
      [
        "KRULISH",
        "Krulish Jct",
        19
      ],
      [
        "NASSAU",
        "Wilson City / N41 or N42 (S)",
        23
      ],
      [
        "BANK",
        "",
        3
      ],
      [
        "",
        "Green Mountain (S)",
        15
      ],
      [
        "CLIFF",
        "Sheffiled (X)",
        11
      ]
    ],
    "block": null,
    "desc": "Express Passenger",
    "loco": null,
    "normalloco": null,
    "origin": {
      "loc": "YD",
      "track": "Y50"
    },
    "terminus": {
      "loc": "CF",
      "track": null
    },
    "sequence": [
      {
        "block": "Y20",
        "os": "YOSKL1",
        "route": "YRtY20Y50",
        "signal": "Y26RA",
        "time": 5000,
        "trigger": "Front"
      },
      {
        "block": "Y21",
        "os": "YOSEJE",
        "route": "YRtY20Y21",
        "signal": "Y10R",
        "time": 5000,
        "trigger": "Front"
      },
      {
        "block": "L20",
        "os": "YOSCJE",
        "route": "YRtY21L20",
        "signal": "Y4R",
        "time": 5000,
        "trigger": "Front"
      },
      {
        "block": "L21",
        "os": "LOSLAM",
        "route": "LRtL20L21",
        "signal": "L6RA",
        "time": 5000,
        "trigger": "Front"
      },
      {
        "block": "D20",
        "os": "LOSCAM",
        "route": "LRtL21D20",
        "signal": "L16R",
        "time": 5000,
        "trigger": "Front"
      },
      {
        "block": "D21",
        "os": "DOSVJE",
        "route": "DRtD20D21",
        "signal": "D4RA",
        "time": 5000,
        "trigger": "Front"
      },
      {
        "block": "S20",
        "os": "DOSFOE",
        "route": "DRtD21S20",
        "signal": "D10R",
        "time": 5000,
        "trigger": "Front"
      },
      {
        "block": "S21",
        "os": "SOSE",
        "route": "SRtS20S21",
        "signal": "S4R",
        "time": 5000,
        "trigger": "Front"
      },
      {
        "block": "N20",
        "os": "KOSN20S21",
        "route": "KRtN20S21",
        "signal": "S21E",
        "time": 5000,
        "trigger": "Front"
      },
      {
        "block": "N21",
        "os": "KOSE",
        "route": "KRtN20N21",
        "signal": "K2R",
        "time": 5000,
        "trigger": "Front"
      },
      {
        "block": "N41",
        "os": "NWOSE",
        "route": "NRtN21N41",
        "signal": "N14R",
        "time": 5000,
        "trigger": "Front"
      },
      {
        "block": "B20",
        "os": "NEOSE",
        "route": "NRtB20N41",
        "signal": "N24RB",
        "time": 5000,
        "trigger": "Front"
      },
      {
        "block": "B21",
        "os": "BOSWE",
        "route": "BRtB20B21",
        "signal": "C24R",
        "time": 5000,
        "trigger": "Front"
      },
      {
        "block": "C13",
        "os": "BOSE",
        "route": "BRtB21C13",
        "signal": "C18RA",
        "time": 5000,
        "trigger": "Front"
      },
      {
        "block": "C12",
        "os": "COSCLW",
        "route": "CRtC13C12",
        "signal": "C14R",
        "time": 5000,
        "trigger": "Front"
      },
      {
        "block": "C11",
        "os": "COSCLEE",
        "route": "CRtC12C11",
        "signal": "C12R",
        "time": 5000,
        "trigger": "Front"
      },
      {
        "block": "C30",
        "os": "COSGMW",
        "route": "CRtC11C30",
        "signal": "C4R",
        "time": 5000,
        "trigger": "Front"
      },
      {
        "block": "C20",
        "os": "COSGME",
        "route": "CRtC30C20",
        "signal": "C2RA",
        "time": 5000,
        "trigger": "Front"
      }
    ],
    "startblock": "Y50",
    "startsubblock": null,
    "time": 5000,
    "eastbound": true
  },
  "21": {
    "tracker": [
      [
        "NASSAU",
        "(From Coach Yard to)",
        22
      ],
      [
        "   Start",
        "Wilson City / N31 or N32",
        23
      ],
      [
        "",
        "Krulish Jct",
        19
      ],
      [
        "SHORE",
        "",
        6
      ],
      [
        "",
        "Bortell (S)",
        3
      ],
      [
        "",
        "Loland (S)",
        26
      ],
      [
        "DELL",
        "Laporte (S)",
        21
      ],
      [
        "LATHAM",
        "Carlton (S)",
        15
      ],
      [
        "PORT",
        "Southport (X)",
        16
      ]
    ],
    "block": null,
    "desc": "Local Passenger",
    "loco": null,
    "normalloco": null,
    "origin": {
      "loc": "WC",
      "track": "N31"
    },
    "terminus": {
      "loc": "PT",
      "track": null
    },
    "sequence": [
      {
        "block": "N32",
        "os": "NEOSW",
        "route": "NRtB10N32",
        "signal": "N26L",
        "time": 5000,
        "trigger": "Front"
      },
      {
        "block": "N11",
        "os": "NWOSW",
        "route": "NRtN11N32",
        "signal": "N18LA",
        "time": 5000,
        "trigger": "Front"
      },
      {
        "block": "N25",
        "os": "KOSM",
        "route": "KRtN25N11",
        "signal": "K8LB",
        "time": 5000,
        "trigger": "Front"
      },
      {
        "block": "P42",
        "os": "SOSHJE",
        "route": "SRtP42N25",
        "signal": "S16L",
        "time": 5000,
        "trigger": "Front"
      },
      {
        "block": "P41",
        "os": "POSCJ2",
        "route": "PRtP41P42",
        "signal": "PB12L",
        "time": 5000,
        "trigger": "Front"
      }
    ],
    "startblock": "B10",
    "startsubblock": null,
    "time": 5000,
    "eastbound": false
  },
  "22": {
    "tracker": [
      [
        "PORT",
        "Southport / P5",
        16
      ],
      [
        "LATHAM",
        "Latham Jct",
        10
      ],
      [
        "",
        "Carlton (S)",
        15
      ],
      [
        "DELL",
        "Laporte (S)",
        21
      ],
      [
        "",
        "Loland (S)",
        26
      ],
      [
        "SHORE",
        "",
        6
      ],
      [
        "KRULISH",
        "Krulish Jct",
        19
      ],
      [
        "NASSAU",
        "Wilson City / N41 or N42 (X)",
        23
      ],
      [
        "",
        "To Coach Yard",
        22
      ]
    ],
    "block": null,
    "desc": "Local Passenger",
    "loco": null,
    "normalloco": null,
    "origin": {
      "loc": "PT",
      "track": null
    },
    "terminus": {
      "loc": "WC",
      "track": "N41"
    },
    "sequence": [
      {
        "block": "P20",
        "os": "POSSP3",
        "route": "PRtP5P20",
        "signal": "PA10RB",
        "time": 5000,
        "trigger": "Front"
      },
      {
        "block": "P21",
        "os": "POSPJ2",
        "route": "PRtP20P21",
        "signal": "PA32L",
        "time": 5000,
        "trigger": "Front"
      },
      {
        "block": "L31",
        "os": "LOSLAE",
        "route": "LRtP21L31",
        "signal": "L4R",
        "time": 5000,
        "trigger": "Front"
      },
      {
        "block": "D20",
        "os": "LOSCAE",
        "route": "LRtL31D20",
        "signal": "L14R",
        "time": 5000,
        "trigger": "Front"
      },
      {
        "block": "D21",
        "os": "DOSVJE",
        "route": "DRtD20D21",
        "signal": "D4RA",
        "time": 5000,
        "trigger": "Front"
      },
      {
        "block": "S20",
        "os": "DOSFOE",
        "route": "DRtD21S20",
        "signal": "D10R",
        "time": 5000,
        "trigger": "Front"
      },
      {
        "block": "S21",
        "os": "SOSE",
        "route": "SRtS20S21",
        "signal": "S4R",
        "time": 5000,
        "trigger": "Front"
      },
      {
        "block": "N20",
        "os": "KOSN20S21",
        "route": "KRtN20S21",
        "signal": "S21E",
        "time": 5000,
        "trigger": "Front"
      },
      {
        "block": "N21",
        "os": "KOSE",
        "route": "KRtN20N21",
        "signal": "K2R",
        "time": 5000,
        "trigger": "Front"
      }
    ],
    "startblock": "P5",
    "startsubblock": null,
    "time": 5000,
    "eastbound": true
  },
  "43": {
    "tracker": [
      [
        "CLIFF",
        "Green Mountain / C30",
        11
      ],
      [
        "",
        "Clivedon (S)",
        10
      ],
      [
        "",
        "Spikes Peak (S)",
        5
      ],
      [
        "BANK",
        "Martinsville (S)",
        3
      ],
      [
        "NASSAU",
        "Wilson City / N31 or N32 (X)",
        23
      ],
      [
        "",
        "Opt (To Coach Yard)",
        22
      ]
    ],
    "block": null,
    "desc": "Local Passenger",
    "loco": null,
    "normalloco": null,
    "origin": {
      "loc": "GM",
      "track": "C30"
    },
    "terminus": {
      "loc": "WC",
      "track": "N31"
    },
    "sequence": [
      {
        "block": "C11",
        "os": "COSGMW",
        "route": "CRtC11C31",
        "signal": "C4LA",
        "time": 5000,
        "trigger": "Front"
      },
      {
        "block": "C23",
        "os": "COSCLEE",
        "route": "CRtC23C11",
        "signal": "C12L",
        "time": 5000,
        "trigger": "Front"
      },
      {
        "block": "C13",
        "os": "COSCLW",
        "route": "CRtC13C23",
        "signal": "C14LB",
        "time": 5000,
        "trigger": "Front"
      },
      {
        "block": "B21",
        "os": "BOSE",
        "route": "BRtB21C13",
        "signal": "C18L",
        "time": 5000,
        "trigger": "Front"
      },
      {
        "block": "B10",
        "os": "BOSWW",
        "route": "BRtB10B21",
        "signal": "C24L",
        "time": 5000,
        "trigger": "Front"
      },
      {
        "block": "N32",
        "os": "NEOSW",
        "route": "NRtB10N32",
        "signal": "N26L",
        "time": 5000,
        "trigger": "Front"
      }
    ],
    "startblock": "C31",
    "startsubblock": null,
    "time": 5000,
    "eastbound": false
  },
  "44": {
    "tracker": [
      [
        "NASSAU",
        "(From Coach Yard to)",
        22
      ],
      [
        "   Start",
        "Wilson City / N41 or N42",
        23
      ],
      [
        "BANK",
        "Martinsville (S)",
        3
      ],
      [
        "",
        "Spikes Peak (S)",
        5
      ],
      [
        "CLIFF",
        "Cliveden (S)",
        10
      ],
      [
        "",
        "Green Mountain / C31 (X)",
        15
      ]
    ],
    "block": null,
    "desc": "Local Passenger",
    "loco": null,
    "normalloco": null,
    "origin": {
      "loc": "WC",
      "track": "N41"
    },
    "terminus": {
      "loc": "GM",
      "track": "C31"
    },
    "sequence": [
      {
        "block": "B20",
        "os": "NEOSE",
        "route": "NRtB20N42",
        "signal": "N24RC",
        "time": 5000,
        "trigger": "Front"
      },
      {
        "block": "B21",
        "os": "BOSWE",
        "route": "BRtB20B21",
        "signal": "C24R",
        "time": 5000,
        "trigger": "Front"
      },
      {
        "block": "C13",
        "os": "BOSE",
        "route": "BRtB21C13",
        "signal": "C18RA",
        "time": 5000,
        "trigger": "Front"
      },
      {
        "block": "C12",
        "os": "COSCLW",
        "route": "CRtC13C12",
        "signal": "C14R",
        "time": 5000,
        "trigger": "Front"
      },
      {
        "block": "C11",
        "os": "COSCLEE",
        "route": "CRtC12C11",
        "signal": "C12R",
        "time": 5000,
        "trigger": "Front"
      },
      {
        "block": "C31",
        "os": "COSGMW",
        "route": "CRtC11C31",
        "signal": "C4R",
        "time": 5000,
        "trigger": "Front"
      }
    ],
    "startblock": "N42",
    "startsubblock": null,
    "time": 5000,
    "eastbound": true
  },
  "56": {
    "tracker": [],
    "block": null,
    "desc": null,
    "loco": null,
    "normalloco": null,
    "origin": {
      "loc": null,
      "track": null
    },
    "terminus": {
      "loc": null,
      "track": null
    },
    "sequence": [
      {
        "block": "Y20",
        "os": "YOSKL3",
        "route": "YRtY20Y60",
        "signal": "Y22R",
        "time": 5000,
        "trigger": "Front"
      },
      {
        "block": "Y21",
        "os": "YOSEJE",
        "route": "YRtY20Y21",
        "signal": "Y10R",
        "time": 5000,
        "trigger": "Front"
      },
      {
        "block": "P50",
        "os": "YOSCJE",
        "route": "YRtY21P50",
        "signal": "Y4R",
        "time": 5000,
        "trigger": "Front"
      },
      {
        "block": "P30",
        "os": "POSPJ2",
        "route": "PRtP30P50",
        "signal": "PA32RB",
        "time": 5000,
        "trigger": "Front"
      },
      {
        "block": "P41",
        "os": "POSSJ1",
        "route": "PRtP30P41",
        "signal": "PB4R",
        "time": 5000,
        "trigger": "Front"
      },
      {
        "block": "P42",
        "os": "POSCJ2",
        "route": "PRtP41P42",
        "signal": "PB12R",
        "time": 5000,
        "trigger": "Front"
      },
      {
        "block": "N25",
        "os": "SOSHJE",
        "route": "SRtP42N25",
        "signal": "S16R",
        "time": 5000,
        "trigger": "Front"
      },
      {
        "block": "N21",
        "os": "KOSM",
        "route": "KRtN25N21",
        "signal": "K4R",
        "time": 5000,
        "trigger": "Front"
      },
      {
        "block": "N41",
        "os": "NWOSE",
        "route": "NRtN21N41",
        "signal": "N14R",
        "time": 5000,
        "trigger": "Front"
      },
      {
        "block": "R10",
        "os": "NEOSRH",
        "route": "NRtR10N41",
        "signal": "N24RB",
        "time": 5000,
        "trigger": "Front"
      }
    ],
    "startblock": "Y60",
    "startsubblock": null,
    "time": 5000,
    "eastbound": true
  },
  "57": {
    "tracker": [],
    "block": null,
    "desc": null,
    "loco": null,
    "normalloco": null,
    "origin": {
      "loc": null,
      "track": null
    },
    "terminus": {
      "loc": null,
      "track": null
    },
    "sequence": [
      {
        "block": "N31",
        "os": "NEOSRH",
        "route": "NRtR10N31",
        "signal": "N28L",
        "time": 5000,
        "trigger": "Front"
      },
      {
        "block": "N11",
        "os": "NWOSW",
        "route": "NRtN11N31",
        "signal": "N18LB",
        "time": 5000,
        "trigger": "Front"
      },
      {
        "block": "N25",
        "os": "KOSM",
        "route": "KRtN25N11",
        "signal": "K8LB",
        "time": 5000,
        "trigger": "Front"
      },
      {
        "block": "P42",
        "os": "SOSHJE",
        "route": "SRtP42N25",
        "signal": "S16L",
        "time": 5000,
        "trigger": "Front"
      },
      {
        "block": "P41",
        "os": "POSCJ2",
        "route": "PRtP41P42",
        "signal": "PB12L",
        "time": 5000,
        "trigger": "Front"
      },
      {
        "block": "P30",
        "os": "POSSJ1",
        "route": "PRtP30P41",
        "signal": "PB2L",
        "time": 5000,
        "trigger": "Front"
      },
      {
        "block": "P50",
        "os": "POSPJ2",
        "route": "PRtP30P50",
        "signal": "PA34LA",
        "time": 5000,
        "trigger": "Front"
      },
      {
        "block": "Y11",
        "os": "YOSCJW",
        "route": "YRtY11P50",
        "signal": "Y4LA",
        "time": 5000,
        "trigger": "Front"
      },
      {
        "block": "Y10",
        "os": "YOSEJW",
        "route": "YRtY10Y11",
        "signal": "Y8L",
        "time": 5000,
        "trigger": "Front"
      },
      {
        "block": "Y60",
        "os": "YOSKL3",
        "route": "YRtY10Y60",
        "signal": "Y22L",
        "time": 5000,
        "trigger": "Front"
      }
    ],
    "startblock": "R10",
    "startsubblock": null,
    "time": 5000,
    "eastbound": true
  },
  "61": {
    "tracker": [
      [
        "NASSAU",
        "(From Coach Yard to)",
        22
      ],
      [
        "   Start",
        "Wilson City / N31 or N32",
        23
      ],
      [
        "KRULISH",
        "Krulish Jct",
        19
      ],
      [
        "",
        "Richards (S)",
        9
      ],
      [
        "",
        "Radstock (S)",
        14
      ],
      [
        "",
        "South Jct",
        9
      ],
      [
        "PORT",
        "Southport (X)",
        16
      ]
    ],
    "block": null,
    "desc": "Local Passenger (RDC)",
    "loco": null,
    "normalloco": null,
    "origin": {
      "loc": "NA",
      "track": null
    },
    "terminus": {
      "loc": "PT",
      "track": null
    },
    "sequence": [
      {
        "block": "N11",
        "os": "NWOSW",
        "route": "NRtN11N31",
        "signal": "N18LB",
        "time": 5000,
        "trigger": "Front"
      },
      {
        "block": "N25",
        "os": "KOSM",
        "route": "KRtN25N11",
        "signal": "K8LB",
        "time": 5000,
        "trigger": "Front"
      },
      {
        "block": "P42",
        "os": "SOSHJE",
        "route": "SRtP42N25",
        "signal": "S16L",
        "time": 5000,
        "trigger": "Front"
      },
      {
        "block": "P41",
        "os": "POSCJ2",
        "route": "PRtP41P42",
        "signal": "PB12L",
        "time": 5000,
        "trigger": "Front"
      },
      {
        "block": "P40",
        "os": "POSSJ2",
        "route": "PRtP40P41",
        "signal": "PB2L",
        "time": 5000,
        "trigger": "Front"
      }
    ],
    "startblock": "N31",
    "startsubblock": null,
    "time": 5000,
    "eastbound": false
  },
  "62": {
    "tracker": [
      [
        "PORT",
        "Southport",
        16
      ],
      [
        "",
        "Radstock (S)",
        14
      ],
      [
        "",
        "Richards (S)",
        9
      ],
      [
        "KRULISH",
        "Krulish Jct",
        19
      ],
      [
        "NASSAU",
        "Wilson City / N41 or N42 (X)",
        23
      ],
      [
        "",
        "(To Coach Yard / A)",
        22
      ]
    ],
    "block": null,
    "desc": "Local Passenger",
    "loco": null,
    "normalloco": null,
    "origin": {
      "loc": "PT",
      "track": null
    },
    "terminus": {
      "loc": "NA",
      "track": null
    },
    "sequence": [],
    "startblock": null,
    "startsubblock": null,
    "time": null,
    "eastbound": true
  },
  "63": {
    "tracker": [
      [
        "PORT",
        "Southport",
        16
      ],
      [
        "",
        "Parsons Jct",
        9
      ],
      [
        "",
        "Cornell Jct",
        7
      ],
      [
        "YARD",
        "Koehlstadt",
        1
      ]
    ],
    "block": null,
    "desc": "Local Passenger (RDC)",
    "loco": null,
    "normalloco": null,
    "origin": {
      "loc": "PT",
      "track": null
    },
    "terminus": {
      "loc": "YD",
      "track": null
    },
    "sequence": [],
    "startblock": null,
    "startsubblock": null,
    "time": null,
    "eastbound": false
  },
  "64": {
    "tracker": [
      [
        "YARD",
        "Koehlstadt",
        1
      ],
      [
        "",
        "Cornell Jct",
        7
      ],
      [
        "",
        "Parsons Jct",
        9
      ],
      [
        "PORT",
        "Southport",
        16
      ]
    ],
    "block": null,
    "desc": "Express Passenger (RDC)",
    "loco": null,
    "normalloco": null,
    "origin": {
      "loc": "YD",
      "track": null
    },
    "terminus": {
      "loc": "PT",
      "track": null
    },
    "sequence": [
      {
        "block": "Y20",
        "os": "YOSKL1",
        "route": "YRtY20Y52",
        "signal": "Y24RA",
        "time": 5000,
        "trigger": "Front"
      },
      {
        "block": "Y21",
        "os": "YOSEJE",
        "route": "YRtY20Y21",
        "signal": "Y10R",
        "time": 5000,
        "trigger": "Front"
      },
      {
        "block": "P50",
        "os": "YOSCJE",
        "route": "YRtY21P50",
        "signal": "Y4R",
        "time": 5000,
        "trigger": "Front"
      },
      {
        "block": "P30",
        "os": "POSPJ2",
        "route": "PRtP30P50",
        "signal": "PA32RB",
        "time": 5000,
        "trigger": "Front"
      },
      {
        "block": "P41",
        "os": "POSSJ1",
        "route": "PRtP30P41",
        "signal": "PB4R",
        "time": 5000,
        "trigger": "Front"
      },
      {
        "block": "P42",
        "os": "POSCJ2",
        "route": "PRtP41P42",
        "signal": "PB12R",
        "time": 5000,
        "trigger": "Front"
      },
      {
        "block": "N25",
        "os": "SOSHJE",
        "route": "SRtP42N25",
        "signal": "S16R",
        "time": 5000,
        "trigger": "Front"
      },
      {
        "block": "N21",
        "os": "KOSM",
        "route": "KRtN25N21",
        "signal": "K4R",
        "time": 5000,
        "trigger": "Front"
      },
      {
        "block": "N31",
        "os": "NWOSE",
        "route": "NRtN21N31",
        "signal": "N14R",
        "time": 5000,
        "trigger": "Front"
      }
    ],
    "startblock": "Y52",
    "startsubblock": null,
    "time": 5000,
    "eastbound": true
  },
  "71": {
    "tracker": [
      [
        "HYDE W",
        "Hidden / H34",
        11
      ],
      [
        "SHORE",
        "",
        6
      ],
      [
        "",
        "Bortell",
        4
      ],
      [
        "",
        "Loland",
        26
      ],
      [
        "DELL",
        "LaPorte",
        21
      ],
      [
        "",
        "Carlton",
        15
      ],
      [
        "LATHAM",
        "",
        10
      ],
      [
        "",
        "Parsons Jct",
        9
      ],
      [
        "PORT",
        "Southport (X)",
        16
      ]
    ],
    "block": null,
    "desc": "Express Passenger",
    "loco": null,
    "normalloco": null,
    "origin": {
      "loc": "HY",
      "track": "H34"
    },
    "terminus": {
      "loc": "PT",
      "track": null
    },
    "sequence": [
      {
        "block": "H11",
        "os": "HOSWW",
        "route": "HRtH11H34",
        "signal": "H6LC",
        "time": 5000,
        "trigger": "Front"
      },
      {
        "block": "H10",
        "os": "SOSHJW",
        "route": "SRtH10H11",
        "signal": "S20L",
        "time": 5000,
        "trigger": "Front"
      },
      {
        "block": "S10",
        "os": "SOSW",
        "route": "SRtS10H10",
        "signal": "S12LC",
        "time": 5000,
        "trigger": "Front"
      },
      {
        "block": "D11",
        "os": "DOSFOW",
        "route": "DRtD11S10",
        "signal": "D12L",
        "time": 5000,
        "trigger": "Front"
      },
      {
        "block": "D10",
        "os": "DOSVJW",
        "route": "DRtD10D11",
        "signal": "D6L",
        "time": 5000,
        "trigger": "Front"
      },
      {
        "block": "L11",
        "os": "LOSCAW",
        "route": "LRtL11D10",
        "signal": "L18L",
        "time": 5000,
        "trigger": "Front"
      },
      {
        "block": "P11",
        "os": "LOSLAM",
        "route": "LRtP11L11",
        "signal": "L8L",
        "time": 5000,
        "trigger": "Front"
      }
    ],
    "startblock": "H34",
    "startsubblock": null,
    "time": 5000,
    "eastbound": false
  },
  "72": {
    "tracker": [
      [
        "PORT",
        "Southport / P4",
        16
      ],
      [
        "LATHAM",
        "",
        10
      ],
      [
        "",
        "Carlton",
        15
      ],
      [
        "DELL",
        "LaPorte",
        21
      ],
      [
        "",
        "Loland",
        26
      ],
      [
        "",
        "Bortell",
        5
      ],
      [
        "SHORE",
        "",
        6
      ],
      [
        "HYDE W",
        "Hidden / H43 (X)",
        11
      ]
    ],
    "block": null,
    "desc": "Express Passenger",
    "loco": null,
    "normalloco": null,
    "origin": {
      "loc": "PT",
      "track": null
    },
    "terminus": {
      "loc": "HY",
      "track": "H43"
    },
    "sequence": [
      {
        "block": "P20",
        "os": "POSSP3",
        "route": "PRtP4P20",
        "signal": "PA8R",
        "time": 5000,
        "trigger": "Front"
      },
      {
        "block": "P21",
        "os": "POSPJ2",
        "route": "PRtP20P21",
        "signal": "PA32L",
        "time": 5000,
        "trigger": "Front"
      },
      {
        "block": "L31",
        "os": "LOSLAE",
        "route": "LRtP21L31",
        "signal": "L4R",
        "time": 5000,
        "trigger": "Front"
      },
      {
        "block": "D20",
        "os": "LOSCAE",
        "route": "LRtL31D20",
        "signal": "L14R",
        "time": 5000,
        "trigger": "Front"
      },
      {
        "block": "D21",
        "os": "DOSVJE",
        "route": "DRtD20D21",
        "signal": "D4RA",
        "time": 5000,
        "trigger": "Front"
      },
      {
        "block": "S20",
        "os": "DOSFOE",
        "route": "DRtD21S20",
        "signal": "D10R",
        "time": 5000,
        "trigger": "Front"
      },
      {
        "block": "H20",
        "os": "SOSE",
        "route": "SRtS20H20",
        "signal": "S4R",
        "time": 5000,
        "trigger": "Front"
      },
      {
        "block": "H21",
        "os": "SOSHJM",
        "route": "SRtH20H21",
        "signal": "S18R",
        "time": 5000,
        "trigger": "Front"
      },
      {
        "block": "H42",
        "os": "HOSWE",
        "route": "HRtH21H42",
        "signal": "H4R",
        "time": 5000,
        "trigger": "Front"
      }
    ],
    "startblock": "P4",
    "startsubblock": null,
    "time": 5000,
    "eastbound": true
  },
  "73": {
    "tracker": [
      [
        "HYDE W",
        "Hidden / H12",
        11
      ],
      [
        "SHORE",
        "",
        6
      ],
      [
        "",
        "Bortell",
        4
      ],
      [
        "",
        "Loland",
        26
      ],
      [
        "DELL",
        "Laporte",
        21
      ],
      [
        "HYDE E",
        "Hidden / H34 (X)",
        11
      ]
    ],
    "block": null,
    "desc": "Loop Passenger",
    "loco": null,
    "normalloco": null,
    "origin": {
      "loc": "HY",
      "track": "H12"
    },
    "terminus": {
      "loc": "HY",
      "track": "H34"
    },
    "sequence": [
      {
        "block": "H11",
        "os": "HOSWW",
        "route": "HRtH11H12",
        "signal": "H6LD",
        "time": 5000,
        "trigger": "Front"
      },
      {
        "block": "H10",
        "os": "SOSHJW",
        "route": "SRtH10H11",
        "signal": "S20L",
        "time": 5000,
        "trigger": "Front"
      },
      {
        "block": "S10",
        "os": "SOSW",
        "route": "SRtS10H10",
        "signal": "S12LC",
        "time": 5000,
        "trigger": "Front"
      },
      {
        "block": "D11",
        "os": "DOSFOW",
        "route": "DRtD11S10",
        "signal": "D12L",
        "time": 5000,
        "trigger": "Front"
      },
      {
        "block": "H13",
        "os": "DOSVJW",
        "route": "DRtH13D11",
        "signal": "D6L",
        "time": 5000,
        "trigger": "Front"
      },
      {
        "block": "H34",
        "os": "HOSEW",
        "route": "HRtH13H34",
        "signal": "H12L",
        "time": 5000,
        "trigger": "Front"
      }
    ],
    "startblock": "H12",
    "startsubblock": null,
    "time": 5000,
    "eastbound": false
  },
  "81": {
    "tracker": [
      [
        "CLIFF",
        "Sheffield ",
        11
      ],
      [
        "BANK",
        "",
        3
      ],
      [
        "NASSAU",
        "Wilson City / N31 or N32 (S)",
        23
      ],
      [
        "",
        "Krulish Jct",
        19
      ],
      [
        "SHORE",
        "",
        6
      ],
      [
        "",
        "Bortell",
        4
      ],
      [
        "",
        "Loland",
        26
      ],
      [
        "DELL",
        "Laporte",
        21
      ],
      [
        "HYDE E",
        "Hidden / H12 (X)",
        11
      ]
    ],
    "block": null,
    "desc": "Express Passenger",
    "loco": null,
    "normalloco": null,
    "origin": {
      "loc": "CF",
      "track": null
    },
    "terminus": {
      "loc": "HY",
      "track": "H12"
    },
    "sequence": [
      {
        "block": "C23",
        "os": "COSCLEW",
        "route": "CRtC23C22",
        "signal": "C10L",
        "time": 5000,
        "trigger": "Front"
      },
      {
        "block": "C13",
        "os": "COSCLW",
        "route": "CRtC13C23",
        "signal": "C14LB",
        "time": 5000,
        "trigger": "Front"
      },
      {
        "block": "B11",
        "os": "BOSE",
        "route": "BRtB11C13",
        "signal": "C18L",
        "time": 5000,
        "trigger": "Front"
      },
      {
        "block": "B10",
        "os": "BOSWW",
        "route": "BRtB10B11",
        "signal": "C22L",
        "time": 5000,
        "trigger": "Front"
      },
      {
        "block": "N31",
        "os": "NEOSW",
        "route": "NRtB10N31",
        "signal": "N26L",
        "time": 5000,
        "trigger": "Front"
      },
      {
        "block": "N11",
        "os": "NWOSW",
        "route": "NRtN11N31",
        "signal": "N18LB",
        "time": 5000,
        "trigger": "Front"
      },
      {
        "block": "N10",
        "os": "KOSW",
        "route": "KRtN10N11",
        "signal": "K8LB",
        "time": 5000,
        "trigger": "Front"
      },
      {
        "block": "S11",
        "os": "KOSN10S11",
        "route": "KRtN10S11",
        "signal": "N10W",
        "time": 5000,
        "trigger": "Front"
      },
      {
        "block": "S10",
        "os": "SOSW",
        "route": "SRtS10S11",
        "signal": "S12LA",
        "time": 5000,
        "trigger": "Front"
      },
      {
        "block": "D11",
        "os": "DOSFOW",
        "route": "DRtD11S10",
        "signal": "D12L",
        "time": 5000,
        "trigger": "Front"
      },
      {
        "block": "H13",
        "os": "DOSVJW",
        "route": "DRtH13D11",
        "signal": "D6L",
        "time": 5000,
        "trigger": "Front"
      },
      {
        "block": "H12",
        "os": "HOSEW",
        "route": "HRtH12H13",
        "signal": "H12L",
        "time": 5000,
        "trigger": "Front"
      }
    ],
    "startblock": "C22",
    "startsubblock": null,
    "time": 5000,
    "eastbound": false
  },
  "82": {
    "tracker": [
      [
        "HYDE E",
        "Hidden / H42",
        11
      ],
      [
        "DELL",
        "Laporte",
        21
      ],
      [
        "SHORE",
        "",
        6
      ],
      [
        "KRULISH",
        "Krulish Jct",
        19
      ],
      [
        "NASSAU",
        "Wilson City /N41 or N42 (S)",
        23
      ],
      [
        "BANK",
        "",
        3
      ],
      [
        "CLIFF",
        "Green Mountain (S)",
        15
      ],
      [
        "",
        "Sheffield Yd (X)",
        11
      ]
    ],
    "block": null,
    "desc": "Express Passenger",
    "loco": null,
    "normalloco": null,
    "origin": {
      "loc": "HY",
      "track": "H42"
    },
    "terminus": {
      "loc": "CF",
      "track": null
    },
    "sequence": [
      {
        "block": "H23",
        "os": "HOSEE",
        "route": "HRtH23H42",
        "signal": "H10RC",
        "time": 5000,
        "trigger": "Front"
      },
      {
        "block": "D21",
        "os": "DOSVJE",
        "route": "DRtH23D21",
        "signal": "D4RB",
        "time": 5000,
        "trigger": "Front"
      },
      {
        "block": "S20",
        "os": "DOSFOE",
        "route": "DRtD21S20",
        "signal": "D10R",
        "time": 5000,
        "trigger": "Front"
      },
      {
        "block": "S21",
        "os": "SOSE",
        "route": "SRtS20S21",
        "signal": "S4R",
        "time": 5000,
        "trigger": "Front"
      },
      {
        "block": "N20",
        "os": "KOSN20S21",
        "route": "KRtN20S21",
        "signal": "S21E",
        "time": 5000,
        "trigger": "Front"
      },
      {
        "block": "N21",
        "os": "KOSE",
        "route": "KRtN20N21",
        "signal": "K2R",
        "time": 5000,
        "trigger": "Front"
      },
      {
        "block": "N41",
        "os": "NWOSE",
        "route": "NRtN21N41",
        "signal": "N14R",
        "time": 5000,
        "trigger": "Front"
      },
      {
        "block": "B20",
        "os": "NEOSE",
        "route": "NRtB20N41",
        "signal": "N24RB",
        "time": 5000,
        "trigger": "Front"
      },
      {
        "block": "B21",
        "os": "BOSWE",
        "route": "BRtB20B21",
        "signal": "C24R",
        "time": 5000,
        "trigger": "Front"
      },
      {
        "block": "C13",
        "os": "BOSE",
        "route": "BRtB21C13",
        "signal": "C18RA",
        "time": 5000,
        "trigger": "Front"
      },
      {
        "block": "C12",
        "os": "COSCLW",
        "route": "CRtC13C12",
        "signal": "C14R",
        "time": 5000,
        "trigger": "Front"
      },
      {
        "block": "C11",
        "os": "COSCLEE",
        "route": "CRtC12C11",
        "signal": "C12R",
        "time": 5000,
        "trigger": "Front"
      },
      {
        "block": "C30",
        "os": "COSGMW",
        "route": "CRtC11C30",
        "signal": "C4R",
        "time": 5000,
        "trigger": "Front"
      },
      {
        "block": "C20",
        "os": "COSGME",
        "route": "CRtC30C20",
        "signal": "C2RA",
        "time": 5000,
        "trigger": "Front"
      }
    ],
    "startblock": "H42",
    "startsubblock": null,
    "time": 5000,
    "eastbound": true
  },
  "84": {
    "tracker": [
      [
        "HYDE E",
        "Hidden / H43",
        11
      ],
      [
        "DELL",
        "Laporte",
        21
      ],
      [
        "",
        "Loland",
        26
      ],
      [
        "",
        "Bortell",
        4
      ],
      [
        "SHORE",
        "",
        6
      ],
      [
        "HYDE W",
        "Hidden / H42 (X)",
        11
      ]
    ],
    "block": null,
    "desc": "Loop Passenger",
    "loco": null,
    "normalloco": null,
    "origin": {
      "loc": "HY",
      "track": "H43"
    },
    "terminus": {
      "loc": "HY",
      "track": "H42"
    },
    "sequence": [
      {
        "block": "H23",
        "os": "HOSEE",
        "route": "HRtH23H43",
        "signal": "H10RB",
        "time": 5000,
        "trigger": "Front"
      },
      {
        "block": "D21",
        "os": "DOSVJE",
        "route": "DRtH23D21",
        "signal": "D4RB",
        "time": 5000,
        "trigger": "Front"
      },
      {
        "block": "S20",
        "os": "DOSFOE",
        "route": "DRtD21S20",
        "signal": "D10R",
        "time": 5000,
        "trigger": "Front"
      },
      {
        "block": "H20",
        "os": "SOSE",
        "route": "SRtS20H20",
        "signal": "S4R",
        "time": 5000,
        "trigger": "Front"
      },
      {
        "block": "H21",
        "os": "SOSHJM",
        "route": "SRtH20H21",
        "signal": "S18R",
        "time": 5000,
        "trigger": "Front"
      },
      {
        "block": "H42",
        "os": "HOSWE",
        "route": "HRtH21H42",
        "signal": "H4R",
        "time": 5000,
        "trigger": "Front"
      }
    ],
    "startblock": "H43",
    "startsubblock": null,
    "time": 5000,
    "eastbound": true
  },
  "91": {
    "tracker": [
      [
        "",
        "Harpers Ferry / F33",
        7
      ],
      [
        "",
        "Rocky Hill (S)",
        2
      ],
      [
        "NASSAU",
        "Wilson City (N31 or N32)",
        23
      ],
      [
        "",
        "Krulish Jct",
        19
      ],
      [
        "",
        "Richards",
        9
      ],
      [
        "",
        "Radstock",
        14
      ],
      [
        "",
        "South Jct",
        9
      ],
      [
        "PORT",
        "Southport (X)",
        16
      ]
    ],
    "block": null,
    "desc": "Express Passenger",
    "loco": null,
    "normalloco": null,
    "origin": {
      "loc": "HF",
      "track": null
    },
    "terminus": {
      "loc": "PT",
      "track": null
    },
    "sequence": [],
    "startblock": null,
    "startsubblock": null,
    "time": null,
    "eastbound": false
  },
  "92": {
    "tracker": [
      [
        "PORT",
        "Southport",
        16
      ],
      [
        "",
        "Radstock",
        14
      ],
      [
        "",
        "Richards",
        9
      ],
      [
        "KRULISH",
        "Krulish Jct",
        19
      ],
      [
        "NASSAU",
        "Wilson City (N41 or N42)",
        23
      ],
      [
        "Branch",
        "Rocky Hill",
        2
      ],
      [
        "",
        "Harpers Ferry / F33",
        7
      ]
    ],
    "block": null,
    "desc": "Express Passenger",
    "loco": null,
    "normalloco": null,
    "origin": {
      "loc": "PT",
      "track": null
    },
    "terminus": {
      "loc": "HF",
      "track": null
    },
    "sequence": [],
    "startblock": null,
    "startsubblock": null,
    "time": null,
    "eastbound": true
  },
  "95": {
    "tracker": [
      [
        "",
        "Harpers Ferry / F33",
        7
      ],
      [
        "",
        "Rocky Hill (S)",
        2
      ],
      [
        "NASSAU",
        "Wilson City / N31 or N32 (S)",
        23
      ],
      [
        "",
        "Krulish Jct",
        19
      ],
      [
        "SHORE",
        "Bortell (S)",
        4
      ],
      [
        "",
        "Loland (S)",
        26
      ],
      [
        "DELL",
        "Laporte (S)",
        22
      ],
      [
        "LATHAM",
        "Carlton (S)",
        15
      ],
      [
        "YARD",
        "Koehlstadt / Y53 (X)",
        1
      ]
    ],
    "block": null,
    "desc": "Local Passenger",
    "loco": null,
    "normalloco": null,
    "origin": {
      "loc": "HF",
      "track": null
    },
    "terminus": {
      "loc": "YD",
      "track": "Y53"
    },
    "sequence": [],
    "startblock": null,
    "startsubblock": null,
    "time": null,
    "eastbound": false
  },
  "96": {
    "tracker": [
      [
        "YARD",
        "Koehlstadt / Y53",
        1
      ],
      [
        "LATHAM",
        "Carlton (S)",
        10
      ],
      [
        "DELL",
        "LaPorte (S)",
        21
      ],
      [
        "",
        "Loland (S)",
        25
      ],
      [
        "SHORE",
        "Bortell (S)",
        4
      ],
      [
        "",
        "Krulish Jct",
        19
      ],
      [
        "NASSAU",
        "Wilson City / N41 or N42",
        23
      ],
      [
        "Branch",
        "Rocky Hill (S)",
        2
      ],
      [
        "",
        "Harpers Ferry / F33 (X)",
        7
      ]
    ],
    "block": null,
    "desc": "Local Passenger",
    "loco": null,
    "normalloco": null,
    "origin": {
      "loc": "YD",
      "track": "Y53"
    },
    "terminus": {
      "loc": "HF",
      "track": null
    },
    "sequence": [
      {
        "block": "Y20",
        "os": "YOSKL1",
        "route": "YRtY20Y52",
        "signal": "Y24RA",
        "time": 5000,
        "trigger": "Front"
      },
      {
        "block": "Y21",
        "os": "YOSEJE",
        "route": "YRtY20Y21",
        "signal": "Y10R",
        "time": 5000,
        "trigger": "Front"
      },
      {
        "block": "L20",
        "os": "YOSCJE",
        "route": "YRtY21L20",
        "signal": "Y4R",
        "time": 5000,
        "trigger": "Front"
      },
      {
        "block": "L21",
        "os": "LOSLAM",
        "route": "LRtL20L21",
        "signal": "L6RA",
        "time": 5000,
        "trigger": "Front"
      },
      {
        "block": "D20",
        "os": "LOSCAM",
        "route": "LRtL21D20",
        "signal": "L16R",
        "time": 5000,
        "trigger": "Front"
      },
      {
        "block": "D21",
        "os": "DOSVJE",
        "route": "DRtD20D21",
        "signal": "D4RA",
        "time": 5000,
        "trigger": "Front"
      },
      {
        "block": "S20",
        "os": "DOSFOE",
        "route": "DRtD21S20",
        "signal": "D10R",
        "time": 5000,
        "trigger": "Front"
      },
      {
        "block": "S21",
        "os": "SOSE",
        "route": "SRtS20S21",
        "signal": "S4R",
        "time": 5000,
        "trigger": "Front"
      },
      {
        "block": "N20",
        "os": "KOSN20S21",
        "route": "KRtN20S21",
        "signal": "S21E",
        "time": 5000,
        "trigger": "Front"
      },
      {
        "block": "N21",
        "os": "KOSE",
        "route": "KRtN20N21",
        "signal": "K2R",
        "time": 5000,
        "trigger": "Front"
      },
      {
        "block": "N22",
        "os": "NWOSE",
        "route": "NRtN21N22",
        "signal": "N14R",
        "time": 5000,
        "trigger": "Front"
      },
      {
        "block": "R10",
        "os": "NEOSRH",
        "route": "NRtR10N22",
        "signal": "N24RA",
        "time": 5000,
        "trigger": "Front"
      }
    ],
    "startblock": "Y52",
    "startsubblock": null,
    "time": 5000,
    "eastbound": true
  },
  "CFHY": {
    "tracker": [
      [
        "CLIFF",
        "",
        11
      ],
      [
        "BANK",
        "",
        3
      ],
      [
        "NASSAU",
        "",
        23
      ],
      [
        "",
        "Krulish Jct",
        19
      ],
      [
        "SHORE",
        "",
        6
      ],
      [
        "",
        "Bortell",
        4
      ],
      [
        "",
        "Loland",
        26
      ],
      [
        "DELL",
        "Laporte",
        21
      ],
      [
        "HYDE E",
        "Hidden Trk / H33 (X)",
        11
      ]
    ],
    "block": null,
    "desc": "Unit Freight",
    "loco": null,
    "normalloco": null,
    "origin": {
      "loc": "CF",
      "track": null
    },
    "terminus": {
      "loc": "HY",
      "track": "H33"
    },
    "sequence": [
      {
        "block": "C23",
        "os": "COSCLEW",
        "route": "CRtC23C22",
        "signal": "C10L",
        "time": 5000,
        "trigger": "Front"
      },
      {
        "block": "C13",
        "os": "COSCLW",
        "route": "CRtC13C23",
        "signal": "C14LB",
        "time": 5000,
        "trigger": "Front"
      },
      {
        "block": "B11",
        "os": "BOSE",
        "route": "BRtB11C13",
        "signal": "C18L",
        "time": 5000,
        "trigger": "Front"
      },
      {
        "block": "B10",
        "os": "BOSWW",
        "route": "BRtB10B11",
        "signal": "C22L",
        "time": 5000,
        "trigger": "Front"
      },
      {
        "block": "N12",
        "os": "NEOSW",
        "route": "NRtB10N12",
        "signal": "N26L",
        "time": 5000,
        "trigger": "Front"
      },
      {
        "block": "N11",
        "os": "NWOSW",
        "route": "NRtN11N12",
        "signal": "N16L",
        "time": 5000,
        "trigger": "Front"
      },
      {
        "block": "N10",
        "os": "KOSW",
        "route": "KRtN10N11",
        "signal": "K8LB",
        "time": 5000,
        "trigger": "Front"
      },
      {
        "block": "S11",
        "os": "KOSN10S11",
        "route": "KRtN10S11",
        "signal": "N10W",
        "time": 5000,
        "trigger": "Front"
      },
      {
        "block": "S10",
        "os": "SOSW",
        "route": "SRtS10S11",
        "signal": "S12LA",
        "time": 5000,
        "trigger": "Front"
      },
      {
        "block": "D11",
        "os": "DOSFOW",
        "route": "DRtD11S10",
        "signal": "D12L",
        "time": 5000,
        "trigger": "Front"
      },
      {
        "block": "D10",
        "os": "DOSVJW",
        "route": "DRtD10D11",
        "signal": "D6L",
        "time": 5000,
        "trigger": "Front"
      },
      {
        "block": "L11",
        "os": "LOSCAW",
        "route": "LRtL11D10",
        "signal": "L18L",
        "time": 5000,
        "trigger": "Front"
      },
      {
        "block": "L10",
        "os": "LOSLAW",
        "route": "LRtL10L11",
        "signal": "L8L",
        "time": 5000,
        "trigger": "Front"
      },
      {
        "block": "Y11",
        "os": "YOSCJW",
        "route": "YRtY11L10",
        "signal": "Y2L",
        "time": 5000,
        "trigger": "Front"
      },
      {
        "block": "Y87",
        "os": "YOSEJW",
        "route": "YRtY87Y11",
        "signal": "Y8L",
        "time": 5000,
        "trigger": "Front"
      }
    ],
    "startblock": "C22",
    "startsubblock": null,
    "time": 5000,
    "eastbound": false
  },
  "CLYD": {
    "tracker": [],
    "block": null,
    "desc": null,
    "loco": null,
    "normalloco": null,
    "origin": {
      "loc": null,
      "track": null
    },
    "terminus": {
      "loc": null,
      "track": null
    },
    "sequence": [
      {
        "block": "C23",
        "os": "COSCLEW",
        "route": "CRtC23C22",
        "signal": "C10L",
        "time": 5000,
        "trigger": "Front"
      },
      {
        "block": "C13",
        "os": "COSCLW",
        "route": "CRtC13C23",
        "signal": "C14LB",
        "time": 5000,
        "trigger": "Front"
      },
      {
        "block": "B11",
        "os": "BOSE",
        "route": "BRtB11C13",
        "signal": "C18L",
        "time": 5000,
        "trigger": "Front"
      },
      {
        "block": "B10",
        "os": "BOSWW",
        "route": "BRtB10B11",
        "signal": "C22L",
        "time": 5000,
        "trigger": "Front"
      },
      {
        "block": "N12",
        "os": "NEOSW",
        "route": "NRtB10N12",
        "signal": "N26L",
        "time": 5000,
        "trigger": "Front"
      },
      {
        "block": "N11",
        "os": "NWOSW",
        "route": "NRtN11N12",
        "signal": "N16L",
        "time": 5000,
        "trigger": "Front"
      },
      {
        "block": "N10",
        "os": "KOSW",
        "route": "KRtN10N11",
        "signal": "K8LB",
        "time": 5000,
        "trigger": "Front"
      },
      {
        "block": "S11",
        "os": "KOSN10S11",
        "route": "KRtN10S11",
        "signal": "N10W",
        "time": 5000,
        "trigger": "Front"
      },
      {
        "block": "S10",
        "os": "SOSW",
        "route": "SRtS10S11",
        "signal": "S12LA",
        "time": 5000,
        "trigger": "Front"
      },
      {
        "block": "D11",
        "os": "DOSFOW",
        "route": "DRtD11S10",
        "signal": "D12L",
        "time": 5000,
        "trigger": "Front"
      },
      {
        "block": "D10",
        "os": "DOSVJW",
        "route": "DRtD10D11",
        "signal": "D6L",
        "time": 5000,
        "trigger": "Front"
      },
      {
        "block": "L11",
        "os": "LOSCAW",
        "route": "LRtL11D10",
        "signal": "L18L",
        "time": 5000,
        "trigger": "Front"
      },
      {
        "block": "L10",
        "os": "LOSLAW",
        "route": "LRtL10L11",
        "signal": "L8L",
        "time": 5000,
        "trigger": "Front"
      },
      {
        "block": "Y11",
        "os": "YOSCJW",
        "route": "YRtY11L10",
        "signal": "Y2L",
        "time": 5000,
        "trigger": "Front"
      }
    ],
    "startblock": "C22",
    "startsubblock": null,
    "time": 5000,
    "eastbound": false
  },
  "HEX": {
    "tracker": [
      [
        "HYDE E",
        "Hidden / H40",
        11
      ],
      [
        "DELL",
        "",
        21
      ],
      [
        "",
        "Loland",
        25
      ],
      [
        "",
        "Bortell",
        4
      ],
      [
        "SHORE",
        "",
        6
      ],
      [
        "HYDE W",
        "Hidden / H40 (X)",
        11
      ]
    ],
    "block": null,
    "desc": "Empty Coal Hoppers",
    "loco": "7600",
    "normalloco": "7600",
    "origin": {
      "loc": "HY",
      "track": "H40"
    },
    "terminus": {
      "loc": "HY",
      "track": "H40"
    },
    "sequence": [
      {
        "block": "H23",
        "os": "HOSEE",
        "route": "HRtH23H40",
        "signal": "H10RE",
        "time": 5000,
        "trigger": "Front"
      },
      {
        "block": "D21",
        "os": "DOSVJE",
        "route": "DRtH23D21",
        "signal": "D4RB",
        "time": 5000,
        "trigger": "Front"
      },
      {
        "block": "S20",
        "os": "DOSFOE",
        "route": "DRtD21S20",
        "signal": "D10R",
        "time": 4000,
        "trigger": "front"
      },
      {
        "block": "H20",
        "os": "SOSE",
        "route": "SRtS20H20",
        "signal": "S4R",
        "time": 5000,
        "trigger": "Front"
      },
      {
        "block": "H40",
        "os": "SOSHJM",
        "route": "SRtH20H40",
        "signal": "S18R",
        "time": 5000,
        "trigger": "Front"
      }
    ],
    "startblock": "H40",
    "startsubblock": null,
    "time": 5000,
    "eastbound": true
  },
  "HWX": {
    "tracker": [
      [
        "HYDE W",
        "Hidden / H32 ",
        11
      ],
      [
        "SHORE",
        "",
        6
      ],
      [
        "",
        "Bortell",
        4
      ],
      [
        "",
        "Loland",
        26
      ],
      [
        "DELL",
        "Laporte",
        21
      ],
      [
        "HYDE E",
        "Hidden / H32 (X)",
        11
      ]
    ],
    "block": null,
    "desc": "Loaded Coal Hoppers",
    "loco": "3809",
    "normalloco": "3809",
    "origin": {
      "loc": "HY",
      "track": "H32"
    },
    "terminus": {
      "loc": "HY",
      "track": "H32"
    },
    "sequence": [
      {
        "block": "S10",
        "os": "SOSW",
        "route": "SRtS10H30",
        "signal": "S12LB",
        "time": 5000,
        "trigger": "Front"
      },
      {
        "block": "D11",
        "os": "DOSFOW",
        "route": "DRtD11S10",
        "signal": "D12L",
        "time": 5000,
        "trigger": "Front"
      },
      {
        "block": "H13",
        "os": "DOSVJW",
        "route": "DRtH13D11",
        "signal": "D6L",
        "time": 5000,
        "trigger": "Front"
      },
      {
        "block": "H31",
        "os": "HOSEW",
        "route": "HRtH13H31",
        "signal": "H12L",
        "time": 5000,
        "trigger": "Front"
      },
      {
        "block": "H30",
        "os": "HOSWW2",
        "route": "HRtH30H31",
        "signal": "H8L",
        "time": 5000,
        "trigger": "Front"
      }
    ],
    "startblock": "H30",
    "startsubblock": null,
    "time": 7500,
    "eastbound": false
  },
  "HYCF": {
    "tracker": [
      [
        "HYDE W",
        "Hidden / H22",
        11
      ],
      [
        "DELL",
        "Laporte",
        21
      ],
      [
        "",
        "Loland",
        26
      ],
      [
        "",
        "Bortell",
        4
      ],
      [
        "SHORE",
        "",
        6
      ],
      [
        "",
        "Krulish Jct",
        19
      ],
      [
        "NASSAU",
        "",
        23
      ],
      [
        "BANK",
        "",
        3
      ],
      [
        "CLIFF",
        "Sheffield Yd (X)",
        11
      ]
    ],
    "block": null,
    "desc": "Unit Freight",
    "loco": null,
    "normalloco": null,
    "origin": {
      "loc": "HY",
      "track": "H22"
    },
    "terminus": {
      "loc": "CF",
      "track": null
    },
    "sequence": [
      {
        "block": "H23",
        "os": "HOSEE",
        "route": "HRtH22H23",
        "signal": "H10RA",
        "time": 5000,
        "trigger": "Front"
      },
      {
        "block": "D21",
        "os": "DOSVJE",
        "route": "DRtH23D21",
        "signal": "D4RB",
        "time": 5000,
        "trigger": "Front"
      },
      {
        "block": "S20",
        "os": "DOSFOE",
        "route": "DRtD21S20",
        "signal": "D10R",
        "time": 5000,
        "trigger": "Front"
      },
      {
        "block": "S21",
        "os": "SOSE",
        "route": "SRtS20S21",
        "signal": "S4R",
        "time": 5000,
        "trigger": "Front"
      },
      {
        "block": "N20",
        "os": "KOSN20S21",
        "route": "KRtN20S21",
        "signal": "S21E",
        "time": 5000,
        "trigger": "Front"
      },
      {
        "block": "N21",
        "os": "KOSE",
        "route": "KRtN20N21",
        "signal": "K2R",
        "time": 5000,
        "trigger": "Front"
      },
      {
        "block": "N22",
        "os": "NWOSE",
        "route": "NRtN21N22",
        "signal": "N14R",
        "time": 5000,
        "trigger": "Front"
      },
      {
        "block": "B20",
        "os": "NEOSE",
        "route": "NRtB20N22",
        "signal": "N24RA",
        "time": 5000,
        "trigger": "Front"
      },
      {
        "block": "B21",
        "os": "BOSWE",
        "route": "BRtB20B21",
        "signal": "C24R",
        "time": 5000,
        "trigger": "Front"
      },
      {
        "block": "C13",
        "os": "BOSE",
        "route": "BRtB21C13",
        "signal": "C18RA",
        "time": 5000,
        "trigger": "Front"
      },
      {
        "block": "C12",
        "os": "COSCLW",
        "route": "CRtC13C12",
        "signal": "C14R",
        "time": 5000,
        "trigger": "Front"
      },
      {
        "block": "C11",
        "os": "COSCLEE",
        "route": "CRtC12C11",
        "signal": "C12R",
        "time": 5000,
        "trigger": "Front"
      },
      {
        "block": "C10",
        "os": "COSGMW",
        "route": "CRtC11C10",
        "signal": "C4R",
        "time": 5000,
        "trigger": "Front"
      },
      {
        "block": "C20",
        "os": "COSGME",
        "route": "CRtC10C20",
        "signal": "C2RB",
        "time": 5000,
        "trigger": "Front"
      }
    ],
    "startblock": "H22",
    "startsubblock": null,
    "time": 5000,
    "eastbound": true
  },
  "HYYD": {
    "tracker": [
      [
        "HYDE W",
        "Hidden / H33",
        11
      ],
      [
        "SHORE",
        "",
        6
      ],
      [
        "",
        "Bortel",
        4
      ],
      [
        "",
        "Loland",
        26
      ],
      [
        "DELL",
        "Laporte",
        21
      ],
      [
        "",
        "Carlton",
        15
      ],
      [
        "LATHAM",
        "Latham Jct",
        10
      ],
      [
        "",
        "Cornell",
        7
      ],
      [
        "YARD",
        "Waterman Yard (X)",
        1
      ]
    ],
    "block": null,
    "desc": "Unit Freight",
    "loco": null,
    "normalloco": null,
    "origin": {
      "loc": "HY",
      "track": "H33"
    },
    "terminus": {
      "loc": "YD",
      "track": null
    },
    "sequence": [
      {
        "block": "H11",
        "os": "HOSWW",
        "route": "HRtH11H33",
        "signal": "H6LB",
        "time": 5000,
        "trigger": "Front"
      },
      {
        "block": "H10",
        "os": "SOSHJW",
        "route": "SRtH10H11",
        "signal": "S20L",
        "time": 5000,
        "trigger": "Front"
      },
      {
        "block": "S10",
        "os": "SOSW",
        "route": "SRtS10H10",
        "signal": "S12LC",
        "time": 5000,
        "trigger": "Front"
      },
      {
        "block": "D11",
        "os": "DOSFOW",
        "route": "DRtD11S10",
        "signal": "D12L",
        "time": 5000,
        "trigger": "Front"
      },
      {
        "block": "D10",
        "os": "DOSVJW",
        "route": "DRtD10D11",
        "signal": "D6L",
        "time": 5000,
        "trigger": "Front"
      },
      {
        "block": "L11",
        "os": "LOSCAW",
        "route": "LRtL11D10",
        "signal": "L18L",
        "time": 5000,
        "trigger": "Front"
      },
      {
        "block": "L10",
        "os": "LOSLAW",
        "route": "LRtL10L11",
        "signal": "L8L",
        "time": 5000,
        "trigger": "Front"
      },
      {
        "block": "Y11",
        "os": "YOSCJW",
        "route": "YRtY11L10",
        "signal": "Y2L",
        "time": 5000,
        "trigger": "Front"
      },
      {
        "block": "Y87",
        "os": "YOSEJW",
        "route": "YRtY87Y11",
        "signal": "Y8L",
        "time": 5000,
        "trigger": "Front"
      }
    ],
    "startblock": "H33",
    "startsubblock": null,
    "time": 5000,
    "eastbound": false
  },
  "JYL1": {
    "tracker": [
      [
        "JAMES YD",
        "28 st Street / Track B",
        26
      ],
      [
        "NASSAU",
        "",
        25
      ],
      [
        "",
        "Krulish Jct",
        19
      ],
      [
        "SHORE",
        "",
        6
      ],
      [
        "",
        "Loland",
        26
      ],
      [
        "DELL",
        "LaPorte",
        19
      ],
      [
        "LATHAM",
        "Latham / Track L21 (X)",
        10
      ]
    ],
    "block": null,
    "desc": "Island Freight 1",
    "loco": null,
    "normalloco": null,
    "origin": {
      "loc": "JY",
      "track": "B"
    },
    "terminus": {
      "loc": "LA",
      "track": "L21"
    },
    "sequence": [],
    "startblock": null,
    "startsubblock": null,
    "time": null,
    "eastbound": true
  },
  "JYL2": {
    "tracker": [
      [
        "LATHAM",
        "Latham / Track L21",
        10
      ],
      [
        "PORT",
        "Parsons Jct",
        9
      ],
      [
        "HYDE",
        "Hidden - Hyde Jct H41",
        10
      ],
      [
        "DELL",
        "LaPorte",
        19
      ],
      [
        "SHORE",
        "Bortell",
        5
      ],
      [
        "KURLISH",
        "Krulish Jct",
        19
      ],
      [
        "NASSAU W",
        "",
        22
      ],
      [
        "NASSAU E",
        "Branch",
        25
      ],
      [
        "JAMES YD",
        "Beechview / Track C",
        26
      ]
    ],
    "block": null,
    "desc": "Island Freight 1",
    "loco": null,
    "normalloco": null,
    "origin": {
      "loc": "LA",
      "track": "L21"
    },
    "terminus": {
      "loc": "JY",
      "track": "C"
    },
    "sequence": [],
    "startblock": null,
    "startsubblock": null,
    "time": null,
    "eastbound": false
  },
  "JYP1": {
    "tracker": [
      [
        "JAMES YD",
        "28 th Street / Track B",
        26
      ],
      [
        "NASSAU",
        "Branch",
        25
      ],
      [
        "SHORE",
        "",
        6
      ],
      [
        "DELL",
        "LaPorte",
        19
      ],
      [
        "LATHAM",
        "Latham Jct",
        10
      ],
      [
        "PORT",
        "Parsons Jct",
        9
      ],
      [
        "PORT",
        "Radstock / Track P31 (X)",
        14
      ]
    ],
    "block": null,
    "desc": "Island Freight 2",
    "loco": null,
    "normalloco": null,
    "origin": {
      "loc": "JY",
      "track": "B"
    },
    "terminus": {
      "loc": "PT",
      "track": "P31"
    },
    "sequence": [],
    "startblock": null,
    "startsubblock": null,
    "time": null,
    "eastbound": true
  },
  "JYP2": {
    "tracker": [
      [
        "PORT",
        "Radstock / Track P31",
        14
      ],
      [
        "HYDE",
        "Hidden - Hyde / Track H41",
        10
      ],
      [
        "DELL",
        "LaPorte",
        19
      ],
      [
        "",
        "Loland",
        26
      ],
      [
        "SHORE",
        "Bortell",
        5
      ],
      [
        "KRULISH",
        "Kurlish Jct",
        19
      ],
      [
        "NASSAU W",
        "",
        22
      ],
      [
        "NASSAU E",
        "Branch",
        25
      ],
      [
        "JAMES YD",
        "Beechview / Track C (X)",
        26
      ]
    ],
    "block": null,
    "desc": "Island Freight",
    "loco": null,
    "normalloco": null,
    "origin": {
      "loc": "PT",
      "track": "P31"
    },
    "terminus": {
      "loc": "JY",
      "track": "C"
    },
    "sequence": [],
    "startblock": null,
    "startsubblock": null,
    "time": null,
    "eastbound": false
  },
  "PBCX": {
    "tracker": [
      [
        "HYDE W",
        "Hidden / H30",
        11
      ],
      [
        "SHORE",
        "",
        6
      ],
      [
        "",
        "Bortell",
        4
      ],
      [
        "",
        "Loland",
        26
      ],
      [
        "DELL",
        "Laporte",
        21
      ],
      [
        "HYDE E",
        "Hidden / H30 (X)",
        11
      ]
    ],
    "block": null,
    "desc": "Pate Brothers Circus",
    "loco": "4023",
    "normalloco": "4023",
    "origin": {
      "loc": "HY",
      "track": "H30"
    },
    "terminus": {
      "loc": "HY",
      "track": "H30"
    },
    "sequence": [
      {
        "block": "H11",
        "os": "HOSWW",
        "route": "HRtH11H32",
        "signal": "H6LA",
        "time": 5000,
        "trigger": "Front"
      },
      {
        "block": "H10",
        "os": "SOSHJW",
        "route": "SRtH10H11",
        "signal": "S20L",
        "time": 5000,
        "trigger": "Front"
      },
      {
        "block": "S10",
        "os": "SOSW",
        "route": "SRtS10H10",
        "signal": "S12LC",
        "time": 5000,
        "trigger": "Front"
      },
      {
        "block": "D11",
        "os": "DOSFOW",
        "route": "DRtD11S10",
        "signal": "D12L",
        "time": 5000,
        "trigger": "Front"
      },
      {
        "block": "H13",
        "os": "DOSVJW",
        "route": "DRtH13D11",
        "signal": "D6L",
        "time": 5000,
        "trigger": "Front"
      },
      {
        "block": "H32",
        "os": "HOSEW",
        "route": "HRtH13H32",
        "signal": "H12L",
        "time": 5000,
        "trigger": "Front"
      }
    ],
    "startblock": "H32",
    "startsubblock": null,
    "time": 5000,
    "eastbound": false
  },
  "RXE1": {
    "tracker": [
      [
        "YARD",
        "",
        1
      ],
      [
        "",
        "Cornell Jct",
        7
      ],
      [
        "PORT",
        "Parsons Jct",
        9
      ],
      [
        "PORT",
        "South Jct",
        9
      ],
      [
        "",
        "Radstock",
        16
      ],
      [
        "",
        "Richards",
        9
      ],
      [
        "NASSAU",
        "Krulish Jct",
        19
      ],
      [
        "NASSAU",
        "Wilson City / WC20 (X)",
        23
      ]
    ],
    "block": null,
    "desc": "Express Mail Passenger",
    "loco": null,
    "normalloco": null,
    "origin": {
      "loc": "YD",
      "track": null
    },
    "terminus": {
      "loc": "WC",
      "track": "W20"
    },
    "sequence": [],
    "startblock": null,
    "startsubblock": null,
    "time": null,
    "eastbound": true
  },
  "RXE2": {
    "tracker": [
      [
        "NASSAU",
        "Wilson City E / track W20",
        23
      ],
      [
        "BANK",
        "",
        3
      ],
      [
        "",
        "Cliveden",
        10
      ],
      [
        "GREEN MTN",
        "GM Yard / Track G21 (X)",
        15
      ]
    ],
    "block": null,
    "desc": "Express Mail Passenger",
    "loco": null,
    "normalloco": null,
    "origin": {
      "loc": "WC",
      "track": "W20"
    },
    "terminus": {
      "loc": "GM",
      "track": "G21"
    },
    "sequence": [],
    "startblock": null,
    "startsubblock": null,
    "time": null,
    "eastbound": true
  },
  "RXW3": {
    "tracker": [
      [
        "GREEN MTN",
        "GM Yd / Trk G21 ",
        15
      ],
      [
        "CLIFF",
        "Sheffield Yd",
        11
      ],
      [
        "",
        "Cliveden",
        10
      ],
      [
        "BANK",
        "",
        3
      ],
      [
        "NASSAU",
        "Wilson City / Trk W10",
        23
      ],
      [
        "",
        "Krulish / Trk K11 (X)",
        19
      ]
    ],
    "block": null,
    "desc": "Express Passenger",
    "loco": null,
    "normalloco": null,
    "origin": {
      "loc": "GM",
      "track": "G21"
    },
    "terminus": {
      "loc": "KR",
      "track": "K11"
    },
    "sequence": [],
    "startblock": null,
    "startsubblock": null,
    "time": null,
    "eastbound": true
  },
  "RXW4": {
    "tracker": [
      [
        "NASSAU",
        "Krulish YD / Trk K11",
        19
      ],
      [
        "NASSAU",
        "Krulish Jct",
        19
      ],
      [
        "",
        "Radstock",
        9
      ],
      [
        "",
        "Richards",
        14
      ],
      [
        "",
        "Parsons Jct",
        9
      ],
      [
        "",
        "Cornell Jct",
        7
      ],
      [
        "YARD",
        "Koelstadt (X)",
        1
      ]
    ],
    "block": null,
    "desc": "Express Passenger",
    "loco": null,
    "normalloco": null,
    "origin": {
      "loc": "KR",
      "track": "K11"
    },
    "terminus": {
      "loc": "YD",
      "track": null
    },
    "sequence": [],
    "startblock": null,
    "startsubblock": null,
    "time": null,
    "eastbound": false
  },
  "WX1": {
    "tracker": [
      [
        "LAVIN YD",
        "",
        9
      ],
      [
        "LATHAM",
        "",
        10
      ],
      [
        "LATHAM",
        "Carlton / Track L31",
        15
      ],
      [
        "",
        "Siding Switch",
        15
      ],
      [
        "",
        "Track L40",
        15
      ],
      [
        "CARLTON E",
        "Track L42 (X to Load)",
        15
      ]
    ],
    "block": null,
    "desc": "Work Train - Out",
    "loco": null,
    "normalloco": null,
    "origin": {
      "loc": "LV",
      "track": null
    },
    "terminus": {
      "loc": "CA",
      "track": "L42"
    },
    "sequence": [],
    "startblock": null,
    "startsubblock": null,
    "time": null,
    "eastbound": true
  },
  "WX2": {
    "tracker": [
      [
        "CARLTON E",
        "Track L42 (with load)",
        15
      ],
      [
        "",
        "Track L40",
        15
      ],
      [
        "",
        "Switch to Main",
        15
      ],
      [
        "",
        "Carlton / Track L31",
        15
      ],
      [
        "LATHAM",
        "Latham Jct / Switch 9",
        10
      ],
      [
        "LATHAM",
        "Latham Jct / Switch 1",
        10
      ],
      [
        "PORT",
        "Parsons Jct",
        9
      ],
      [
        "LAVIN",
        "Switch 31 to Track V11 >",
        9
      ]
    ],
    "block": null,
    "desc": "Work Train - Back",
    "loco": null,
    "normalloco": null,
    "origin": {
      "loc": "CA",
      "track": "L42"
    },
    "terminus": {
      "loc": "LV",
      "track": "V11"
    },
    "sequence": [],
    "startblock": null,
    "startsubblock": null,
    "time": null,
    "eastbound": false
  },
  "X51": {
    "tracker": [
      [
        "Branch",
        "Beechview / Track A",
        26
      ],
      [
        "NASSAU",
        "Wilson City (S)",
        23
      ],
      [
        "",
        "Wilson City W (B)",
        22
      ]
    ],
    "block": null,
    "desc": "Local Passenger",
    "loco": null,
    "normalloco": null,
    "origin": {
      "loc": "JY",
      "track": "A"
    },
    "terminus": {
      "loc": "NA",
      "track": "B"
    },
    "sequence": [],
    "startblock": null,
    "startsubblock": null,
    "time": null,
    "eastbound": false
  },
  "X52": {
    "tracker": [
      [
        "",
        "Wilson City (B)",
        22
      ],
      [
        "Nassau",
        "Wilson City (S)",
        23
      ],
      [
        "Branch ",
        "",
        26
      ],
      [
        "James Yards",
        "Beechview / Track A (X)",
        26
      ]
    ],
    "block": null,
    "desc": "Local Passenger",
    "loco": null,
    "normalloco": null,
    "origin": {
      "loc": "NA",
      "track": "B"
    },
    "terminus": {
      "loc": "JY",
      "track": "A"
    },
    "sequence": [],
    "startblock": null,
    "startsubblock": null,
    "time": null,
    "eastbound": true
  },
  "X65": {
    "tracker": [
      [
        "",
        "From Coach Yd / C or D",
        22
      ],
      [
        "NASSAU",
        "Wilson City / N31 or N32",
        22
      ],
      [
        "",
        "Krulish Jct",
        19
      ],
      [
        "",
        "Richards (S)",
        9
      ],
      [
        "",
        "Radstock (S)",
        14
      ],
      [
        "PORT",
        "Parsons Jct",
        9
      ],
      [
        "",
        "Cornell",
        7
      ],
      [
        "YARD",
        "Koelstadt Station / (X)",
        1
      ]
    ],
    "block": null,
    "desc": "Local Passenger",
    "loco": null,
    "normalloco": null,
    "origin": {
      "loc": "NA",
      "track": null
    },
    "terminus": {
      "loc": "YD",
      "track": null
    },
    "sequence": [],
    "startblock": null,
    "startsubblock": null,
    "time": null,
    "eastbound": false
  },
  "X66": {
    "tracker": [
      [
        "YARD",
        "Koehlstadt ",
        1
      ],
      [
        "LATHAM",
        "Latham Depot",
        10
      ],
      [
        "",
        "Carlton (S)",
        15
      ],
      [
        "DELL",
        "La Porte",
        19
      ],
      [
        "",
        "Loland (S)",
        26
      ],
      [
        "SHORE",
        "",
        4
      ],
      [
        "",
        "Krulish Jct",
        19
      ],
      [
        "NASSAU",
        "Wilson City / N41 or N42",
        23
      ],
      [
        "",
        "To Coach Track C or D (X)",
        22
      ]
    ],
    "block": null,
    "desc": "Local Passenger",
    "loco": null,
    "normalloco": null,
    "origin": {
      "loc": "YD",
      "track": null
    },
    "terminus": {
      "loc": "NA",
      "track": null
    },
    "sequence": [],
    "startblock": null,
    "startsubblock": null,
    "time": null,
    "eastbound": true
  },
  "X98": {
    "tracker": [
      [
        "NASSAU",
        "Wilson City E / track E",
        24
      ],
      [
        "Branch",
        "Rocky Hill (S)",
        2
      ],
      [
        "Branch",
        "Harpers Ferry",
        7
      ]
    ],
    "block": null,
    "desc": "Local Passenger Old",
    "loco": null,
    "normalloco": null,
    "origin": {
      "loc": "NA",
      "track": "E"
    },
    "terminus": {
      "loc": "HF",
      "track": null
    },
    "sequence": [],
    "startblock": null,
    "startsubblock": null,
    "time": null,
    "eastbound": true
  },
  "X99": {
    "tracker": [
      [
        "Branch",
        "Harpers Ferry",
        7
      ],
      [
        "Branch",
        "Rocky Hill (S)",
        2
      ],
      [
        "NASSAU",
        "Wilson City E / track E",
        24
      ]
    ],
    "block": null,
    "desc": "Local Passenger Old",
    "loco": null,
    "normalloco": null,
    "origin": {
      "loc": "HF",
      "track": null
    },
    "terminus": {
      "loc": "NA",
      "track": "E"
    },
    "sequence": [],
    "startblock": null,
    "startsubblock": null,
    "time": null,
    "eastbound": true
  },
  "YDCF": {
    "tracker": [],
    "block": null,
    "desc": null,
    "loco": null,
    "normalloco": null,
    "origin": {
      "loc": null,
      "track": null
    },
    "terminus": {
      "loc": null,
      "track": null
    },
    "sequence": [
      {
        "block": "Y20",
        "os": "YOSKL1",
        "route": "YRtY20Y70",
        "signal": "Y26RC",
        "time": 5000,
        "trigger": "Front"
      },
      {
        "block": "Y21",
        "os": "YOSEJE",
        "route": "YRtY20Y21",
        "signal": "Y10R",
        "time": 5000,
        "trigger": "Front"
      },
      {
        "block": "L20",
        "os": "YOSCJE",
        "route": "YRtY21L20",
        "signal": "Y4R",
        "time": 5000,
        "trigger": "Front"
      },
      {
        "block": "L21",
        "os": "LOSLAM",
        "route": "LRtL20L21",
        "signal": "L6RA",
        "time": 5000,
        "trigger": "Front"
      },
      {
        "block": "D20",
        "os": "LOSCAM",
        "route": "LRtL21D20",
        "signal": "L16R",
        "time": 5000,
        "trigger": "Front"
      },
      {
        "block": "D21",
        "os": "DOSVJE",
        "route": "DRtD20D21",
        "signal": "D4RA",
        "time": 5000,
        "trigger": "Front"
      },
      {
        "block": "S20",
        "os": "DOSFOE",
        "route": "DRtD21S20",
        "signal": "D10R",
        "time": 5000,
        "trigger": "Front"
      },
      {
        "block": "S21",
        "os": "SOSE",
        "route": "SRtS20S21",
        "signal": "S4R",
        "time": 5000,
        "trigger": "Front"
      },
      {
        "block": "N20",
        "os": "KOSN20S21",
        "route": "KRtN20S21",
        "signal": "S21E",
        "time": 5000,
        "trigger": "Front"
      },
      {
        "block": "N21",
        "os": "KOSE",
        "route": "KRtN20N21",
        "signal": "K2R",
        "time": 5000,
        "trigger": "Front"
      },
      {
        "block": "N22",
        "os": "NWOSE",
        "route": "NRtN21N22",
        "signal": "N14R",
        "time": 5000,
        "trigger": "Front"
      },
      {
        "block": "B20",
        "os": "NEOSE",
        "route": "NRtB20N22",
        "signal": "N24RA",
        "time": 5000,
        "trigger": "Front"
      },
      {
        "block": "B21",
        "os": "BOSWE",
        "route": "BRtB20B21",
        "signal": "C24R",
        "time": 5000,
        "trigger": "Front"
      },
      {
        "block": "C13",
        "os": "BOSE",
        "route": "BRtB21C13",
        "signal": "C18RA",
        "time": 5000,
        "trigger": "Front"
      },
      {
        "block": "C12",
        "os": "COSCLW",
        "route": "CRtC13C12",
        "signal": "C14R",
        "time": 5000,
        "trigger": "Front"
      },
      {
        "block": "C11",
        "os": "COSCLEE",
        "route": "CRtC12C11",
        "signal": "C12R",
        "time": 5000,
        "trigger": "Front"
      },
      {
        "block": "C30",
        "os": "COSGMW",
        "route": "CRtC11C30",
        "signal": "C4R",
        "time": 5000,
        "trigger": "Front"
      },
      {
        "block": "C20",
        "os": "COSGME",
        "route": "CRtC30C20",
        "signal": "C2RA",
        "time": 5000,
        "trigger": "Front"
      }
    ],
    "startblock": "Y70",
    "startsubblock": null,
    "time": 5000,
    "eastbound": true
  },
  "YDCL": {
    "tracker": [],
    "block": null,
    "desc": null,
    "loco": null,
    "normalloco": null,
    "origin": {
      "loc": null,
      "track": null
    },
    "terminus": {
      "loc": null,
      "track": null
    },
    "sequence": [
      {
        "block": "Y20",
        "os": "YOSKL1",
        "route": "YRtY20Y70",
        "signal": "Y26RC",
        "time": 5000,
        "trigger": "Front"
      },
      {
        "block": "Y21",
        "os": "YOSEJE",
        "route": "YRtY20Y21",
        "signal": "Y10R",
        "time": 5000,
        "trigger": "Front"
      },
      {
        "block": "L20",
        "os": "YOSCJE",
        "route": "YRtY21L20",
        "signal": "Y4R",
        "time": 5000,
        "trigger": "Front"
      },
      {
        "block": "L21",
        "os": "LOSLAM",
        "route": "LRtL20L21",
        "signal": "L6RA",
        "time": 5000,
        "trigger": "Front"
      },
      {
        "block": "D20",
        "os": "LOSCAM",
        "route": "LRtL21D20",
        "signal": "L16R",
        "time": 5000,
        "trigger": "Front"
      },
      {
        "block": "D21",
        "os": "DOSVJE",
        "route": "DRtD20D21",
        "signal": "D4RA",
        "time": 5000,
        "trigger": "Front"
      },
      {
        "block": "S20",
        "os": "DOSFOE",
        "route": "DRtD21S20",
        "signal": "D10R",
        "time": 5000,
        "trigger": "Front"
      },
      {
        "block": "S21",
        "os": "SOSE",
        "route": "SRtS20S21",
        "signal": "S4R",
        "time": 5000,
        "trigger": "Front"
      },
      {
        "block": "N20",
        "os": "KOSN20S21",
        "route": "KRtN20S21",
        "signal": "S21E",
        "time": 5000,
        "trigger": "Front"
      },
      {
        "block": "N21",
        "os": "KOSE",
        "route": "KRtN20N21",
        "signal": "K2R",
        "time": 5000,
        "trigger": "Front"
      },
      {
        "block": "N22",
        "os": "NWOSE",
        "route": "NRtN21N22",
        "signal": "N14R",
        "time": 5000,
        "trigger": "Front"
      },
      {
        "block": "B20",
        "os": "NEOSE",
        "route": "NRtB20N22",
        "signal": "N24RA",
        "time": 5000,
        "trigger": "Front"
      },
      {
        "block": "B21",
        "os": "BOSWE",
        "route": "BRtB20B21",
        "signal": "C24R",
        "time": 5000,
        "trigger": "Front"
      },
      {
        "block": "C13",
        "os": "BOSE",
        "route": "BRtB21C13",
        "signal": "C18RA",
        "time": 5000,
        "trigger": "Front"
      },
      {
        "block": "C12",
        "os": "COSCLW",
        "route": "CRtC13C12",
        "signal": "C14R",
        "time": 5000,
        "trigger": "Front"
      },
      {
        "block": "C11",
        "os": "COSCLEE",
        "route": "CRtC12C11",
        "signal": "C12R",
        "time": 5000,
        "trigger": "Front"
      },
      {
        "block": "C10",
        "os": "COSGMW",
        "route": "CRtC11C10",
        "signal": "C4R",
        "time": 5000,
        "trigger": "Front"
      },
      {
        "block": "C20",
        "os": "COSGME",
        "route": "CRtC10C20",
        "signal": "C2RB",
        "time": 5000,
        "trigger": "Front"
      }
    ],
    "startblock": "Y70",
    "startsubblock": null,
    "time": 5000,
    "eastbound": true
  },
  "YDHY": {
    "tracker": [
      [
        "YARD",
        "Waterman Yd",
        1
      ],
      [
        "",
        "Cornell Jct",
        7
      ],
      [
        "LATHAM",
        "",
        10
      ],
      [
        "",
        "Carlton",
        15
      ],
      [
        "DELL",
        "Laporte",
        21
      ],
      [
        "",
        "Loland",
        26
      ],
      [
        "",
        "Bortell",
        5
      ],
      [
        "SHORE",
        "",
        6
      ],
      [
        "HYDE W",
        "Hidden / H22 (X)",
        11
      ]
    ],
    "block": null,
    "desc": "Unit Freight",
    "loco": null,
    "normalloco": null,
    "origin": {
      "loc": "YD",
      "track": null
    },
    "terminus": {
      "loc": "HY",
      "track": "H22"
    },
    "sequence": [
      {
        "block": "Y20",
        "os": "YOSKL1",
        "route": "YRtY20Y70",
        "signal": "Y26RC",
        "time": 5000,
        "trigger": "Front"
      },
      {
        "block": "Y21",
        "os": "YOSEJE",
        "route": "YRtY20Y21",
        "signal": "Y10R",
        "time": 5000,
        "trigger": "Front"
      },
      {
        "block": "L20",
        "os": "YOSCJE",
        "route": "YRtY21L20",
        "signal": "Y4R",
        "time": 5000,
        "trigger": "Front"
      },
      {
        "block": "L21",
        "os": "LOSLAM",
        "route": "LRtL20L21",
        "signal": "L6RA",
        "time": 5000,
        "trigger": "Front"
      },
      {
        "block": "D20",
        "os": "LOSCAM",
        "route": "LRtL21D20",
        "signal": "L16R",
        "time": 5000,
        "trigger": "Front"
      },
      {
        "block": "D21",
        "os": "DOSVJE",
        "route": "DRtD20D21",
        "signal": "D4RA",
        "time": 5000,
        "trigger": "Front"
      },
      {
        "block": "S20",
        "os": "DOSFOE",
        "route": "DRtD21S20",
        "signal": "D10R",
        "time": 5000,
        "trigger": "Front"
      },
      {
        "block": "H20",
        "os": "SOSE",
        "route": "SRtS20H20",
        "signal": "S4R",
        "time": 5000,
        "trigger": "Front"
      },
      {
        "block": "H21",
        "os": "SOSHJM",
        "route": "SRtH20H21",
        "signal": "S18R",
        "time": 5000,
        "trigger": "Front"
      },
      {
        "block": "H22",
        "os": "HOSWE",
        "route": "HRtH21H22",
        "signal": "H4R",
        "time": 5000,
        "trigger": "Front"
      }
    ],
    "startblock": "Y70",
    "startsubblock": null,
    "time": 5000,
    "eastbound": true
  }
}